CHANGES.txt
bootstrap.py
buildout.cfg
setup.py
src/mysqldbda/DEPENDENCIES.cfg
src/mysqldbda/PACKAGE.cfg
src/mysqldbda/PUBLICATION.cfg
src/mysqldbda/README.txt
src/mysqldbda/SETUP.cfg
src/mysqldbda/__init__.py
src/mysqldbda/adapter.py
src/mysqldbda/configure.zcml
src/mysqldbda/mysqldbda-configure.zcml
src/mysqldbda.egg-info/PKG-INFO
src/mysqldbda.egg-info/SOURCES.txt
src/mysqldbda.egg-info/dependency_links.txt
src/mysqldbda.egg-info/not-zip-safe
src/mysqldbda.egg-info/requires.txt
src/mysqldbda.egg-info/top_level.txt
src/mysqldbda/tests/__init__.py
src/mysqldbda/tests/test_adapter.py
